{
	"routes": [
		{
			"name": "964",
			"color": "#5BC824",
			"text_color": "#FFFFFF",
			"live_line_code": "SMRTBuses964",
			"brand": "SMRTBuses",
			"mode": "bus",
			"supports_routeinfo": true,
			"url": "https://citymapper.com/singapore/l/smrt-964",
			"patterns": [
				{
					"path": [
						[
							1.43776,
							103.78645
						],
						[
							1.43722,
							103.78494
						],
						[
							1.43727,
							103.78483
						],
						[
							1.43743,
							103.78479
						],
						[
							1.43754,
							103.78485
						],
						[
							1.43774,
							103.78543
						],
						[
							1.43787,
							103.78548
						],
						[
							1.43807,
							103.78542
						],
						[
							1.43848,
							103.78659
						],
						[
							1.43847,
							103.78674
						],
						[
							1.43838,
							103.78688
						],
						[
							1.43828,
							103.78697
						],
						[
							1.4378,
							103.78717
						],
						[
							1.43775,
							103.78729
						],
						[
							1.43774,
							103.78737
						],
						[
							1.43821,
							103.78871
						],
						[
							1.43824,
							103.78898
						],
						[
							1.4387,
							103.78995
						],
						[
							1.438732,
							103.790045
						],
						[
							1.43895,
							103.7907
						],
						[
							1.439134,
							103.793002
						],
						[
							1.43921,
							103.79395
						],
						[
							1.43929,
							103.79579
						],
						[
							1.43938,
							103.79664
						],
						[
							1.43948,
							103.79713
						],
						[
							1.439576,
							103.797422
						],
						[
							1.4397,
							103.7978
						],
						[
							1.440789,
							103.800232
						],
						[
							1.44137,
							103.80153
						],
						[
							1.44158,
							103.80165
						],
						[
							1.44182,
							103.80165
						],
						[
							1.442686,
							103.801266
						],
						[
							1.44545,
							103.80004
						],
						[
							1.44565,
							103.79983
						],
						[
							1.445725,
							103.799646
						],
						[
							1.446562,
							103.797586
						],
						[
							1.44665,
							103.79737
						],
						[
							1.44688,
							103.79719
						],
						[
							1.44757,
							103.79686
						],
						[
							1.447922,
							103.79761
						],
						[
							1.449581,
							103.801143
						],
						[
							1.45043,
							103.80295
						],
						[
							1.45122,
							103.80436
						],
						[
							1.44989,
							103.80508
						],
						[
							1.449785,
							103.805189
						],
						[
							1.44965,
							103.80533
						],
						[
							1.44962,
							103.80527
						],
						[
							1.44927,
							103.80558
						],
						[
							1.448173,
							103.806983
						],
						[
							1.44755,
							103.80778
						],
						[
							1.44741,
							103.80814
						],
						[
							1.44739,
							103.80846
						],
						[
							1.44742,
							103.80861
						],
						[
							1.44751,
							103.80886
						],
						[
							1.44786,
							103.80949
						],
						[
							1.447942,
							103.809562
						],
						[
							1.44819,
							103.80978
						],
						[
							1.44808,
							103.80986
						],
						[
							1.44839,
							103.81033
						],
						[
							1.44881,
							103.81061
						],
						[
							1.44916,
							103.81067
						],
						[
							1.45044,
							103.81051
						],
						[
							1.450729,
							103.810444
						],
						[
							1.45119,
							103.81034
						],
						[
							1.45127,
							103.81038
						],
						[
							1.45154,
							103.81078
						],
						[
							1.45172,
							103.81067
						],
						[
							1.45204,
							103.81119
						],
						[
							1.45218,
							103.8113
						],
						[
							1.45231,
							103.81136
						],
						[
							1.45263,
							103.81135
						],
						[
							1.45321,
							103.81105
						],
						[
							1.453276,
							103.810875
						],
						[
							1.45335,
							103.81068
						],
						[
							1.45332,
							103.81059
						],
						[
							1.45348,
							103.81049
						],
						[
							1.45213,
							103.80818
						],
						[
							1.45283,
							103.80779
						],
						[
							1.453064,
							103.807868
						],
						[
							1.4531,
							103.80788
						],
						[
							1.451707,
							103.805457
						],
						[
							1.45022,
							103.80287
						],
						[
							1.449596,
							103.801571
						],
						[
							1.4489,
							103.80012
						],
						[
							1.44835,
							103.79905
						],
						[
							1.448061,
							103.798371
						],
						[
							1.44758,
							103.79724
						],
						[
							1.44737,
							103.79717
						],
						[
							1.44721,
							103.79715
						],
						[
							1.44681,
							103.79736
						],
						[
							1.44667,
							103.79755
						],
						[
							1.446462,
							103.798073
						],
						[
							1.44582,
							103.79969
						],
						[
							1.44572,
							103.79988
						],
						[
							1.44559,
							103.80005
						],
						[
							1.44531,
							103.80022
						],
						[
							1.443495,
							103.801028
						],
						[
							1.44311,
							103.80149
						],
						[
							1.44293,
							103.80153
						],
						[
							1.44283,
							103.80133
						],
						[
							1.44141,
							103.80195
						],
						[
							1.440829,
							103.800656
						],
						[
							1.4404,
							103.7997
						],
						[
							1.43959,
							103.79785
						],
						[
							1.439418,
							103.797335
						],
						[
							1.43941,
							103.79731
						],
						[
							1.43928,
							103.79678
						],
						[
							1.439091,
							103.794227
						],
						[
							1.43886,
							103.7911
						],
						[
							1.43881,
							103.790891
						],
						[
							1.4387,
							103.79043
						],
						[
							1.43813,
							103.78903
						],
						[
							1.43809,
							103.78875
						],
						[
							1.43753,
							103.78723
						],
						[
							1.43766,
							103.78714
						],
						[
							1.43818,
							103.78695
						],
						[
							1.43831,
							103.78687
						],
						[
							1.4384,
							103.78673
						],
						[
							1.4384,
							103.78657
						],
						[
							1.43806,
							103.78562
						],
						[
							1.43793,
							103.78567
						],
						[
							1.43792,
							103.78583
						],
						[
							1.43818,
							103.78659
						],
						[
							1.43813,
							103.78672
						],
						[
							1.43794,
							103.78677
						]
					],
					"stop_points": [
						{
							"id": "SingaporeStop_WoodlandsTempInt_N",
							"path_index": 0
						},
						{
							"id": "SingaporeStop_Blk825_E",
							"path_index": 18
						},
						{
							"id": "SingaporeStop_Blk853_E",
							"path_index": 20
						},
						{
							"id": "SingaporeStop_Blk706_NE",
							"path_index": 25
						},
						{
							"id": "SingaporeStop_OppAdmiraltyStn_E",
							"path_index": 27
						},
						{
							"id": "SingaporeStop_BefAdmiraltyPrSch_NW",
							"path_index": 31
						},
						{
							"id": "SingaporeStop_Blk722_SW",
							"path_index": 34
						},
						{
							"id": "SingaporeStop_AftWoodlandsMart_N",
							"path_index": 35
						},
						{
							"id": "SingaporeStop_OppBlk773_NE",
							"path_index": 39
						},
						{
							"id": "SingaporeStop_AftWoodlandsIndPkE6_E",
							"path_index": 40
						},
						{
							"id": "SingaporeStop_OldChangKeeBldg_SE",
							"path_index": 44
						},
						{
							"id": "SingaporeStop_JordonFoodInd_E",
							"path_index": 48
						},
						{
							"id": "SingaporeStop_Blk15_N",
							"path_index": 55
						},
						{
							"id": "SingaporeStop_OppBlk20_N",
							"path_index": 62
						},
						{
							"id": "SingaporeStop_OppBlk22_W",
							"path_index": 72
						},
						{
							"id": "SingaporeStop_AnixterBldg_SW",
							"path_index": 78
						},
						{
							"id": "SingaporeStop_OppNylectEngrg_SW",
							"path_index": 80
						},
						{
							"id": "SingaporeStop_AftGambasAve_SW",
							"path_index": 82
						},
						{
							"id": "SingaporeStop_Blk774_SW",
							"path_index": 85
						},
						{
							"id": "SingaporeStop_OppWoodlandsMart_E",
							"path_index": 91
						},
						{
							"id": "SingaporeStop_Blk786ACp_SE",
							"path_index": 92
						},
						{
							"id": "SingaporeStop_OppAdmiraltyPrSch_S",
							"path_index": 96
						},
						{
							"id": "SingaporeStop_AdmiraltyStn_S",
							"path_index": 101
						},
						{
							"id": "SingaporeStop_Blk666_W_1",
							"path_index": 104
						},
						{
							"id": "SingaporeStop_Aft888Plaza_W",
							"path_index": 107
						},
						{
							"id": "SingaporeStop_Blk891CCp_W",
							"path_index": 109
						},
						{
							"id": "SingaporeStop_WoodlandsTempInt_N",
							"path_index": 124
						}
					],
					"name": "towards W'Lands Temp Int",
					"id": "964_0",
					"is_circular": true
				}
			],
			"live_availability": 0,
			"ui_color": "#5BC824",
			"long_name": "W'Lands Temp Int - W'Lands Temp Int",
			"aliases": [
				"smrt-964"
			]
		}
	],
	"stops": {
		"SingaporeStop_AnixterBldg_SW": {
			"live_code": "SingaporeStop_AnixterBldg_SW",
			"routes": [
				"SMRTBuses964"
			],
			"brands": [
				"SMRTBuses"
			],
			"name": "Opp W'Lands Spectrum 1",
			"coords": [
				1.453054,
				103.807899
			],
			"stop_code": "46931",
			"bearing": "SW"
		},
		"SingaporeStop_Blk774_SW": {
			"live_code": "SingaporeStop_Blk774_SW",
			"routes": [
				"SMRTBuses169",
				"SMRTBuses858",
				"SMRTBuses964"
			],
			"brands": [
				"SMRTBuses"
			],
			"name": "Blk 774",
			"coords": [
				1.447969,
				103.79841
			],
			"stop_code": "46479",
			"bearing": "SW"
		},
		"SingaporeStop_OldChangKeeBldg_SE": {
			"live_code": "SingaporeStop_OldChangKeeBldg_SE",
			"routes": [
				"SMRTBuses964"
			],
			"brands": [
				"SMRTBuses"
			],
			"name": "Old Chang Kee Bldg",
			"coords": [
				1.44983,
				103.805232
			],
			"stop_code": "46881",
			"bearing": "SE"
		},
		"SingaporeStop_OppBlk22_W": {
			"live_code": "SingaporeStop_OppBlk22_W",
			"routes": [
				"SMRTBuses964"
			],
			"brands": [
				"SMRTBuses"
			],
			"name": "Opp Blk 22",
			"coords": [
				1.453316,
				103.81089
			],
			"stop_code": "46921",
			"bearing": "W"
		},
		"SingaporeStop_AftWoodlandsIndPkE6_E": {
			"live_code": "SingaporeStop_AftWoodlandsIndPkE6_E",
			"routes": [
				"SMRTBuses169",
				"SMRTBuses169A",
				"SMRTBuses169B",
				"SMRTBuses858",
				"SMRTBuses858A",
				"SMRTBuses964"
			],
			"brands": [
				"SMRTBuses"
			],
			"name": "Aft Woodlands Ind Pk E6",
			"coords": [
				1.449644,
				103.801113
			],
			"stop_code": "46481",
			"bearing": "E"
		},
		"SingaporeStop_AftGambasAve_SW": {
			"live_code": "SingaporeStop_AftGambasAve_SW",
			"routes": [
				"SMRTBuses169",
				"SMRTBuses858",
				"SMRTBuses964"
			],
			"brands": [
				"SMRTBuses"
			],
			"name": "Aft Gambas Ave",
			"coords": [
				1.449521,
				103.801607
			],
			"stop_code": "46489",
			"bearing": "SW"
		},
		"SingaporeStop_JordonFoodInd_E": {
			"live_code": "SingaporeStop_JordonFoodInd_E",
			"routes": [
				"SMRTBuses964"
			],
			"brands": [
				"SMRTBuses"
			],
			"name": "Jordon Food Ind",
			"coords": [
				1.448239,
				103.807035
			],
			"stop_code": "46891",
			"bearing": "E"
		},
		"SingaporeStop_OppBlk20_N": {
			"live_code": "SingaporeStop_OppBlk20_N",
			"routes": [
				"SMRTBuses964"
			],
			"brands": [
				"SMRTBuses"
			],
			"name": "Opp Blk 20",
			"coords": [
				1.45069,
				103.810271
			],
			"stop_code": "46911",
			"bearing": "N"
		},
		"SingaporeStop_AdmiraltyStn_S": {
			"live_code": "SingaporeStop_AdmiraltyStn_S",
			"routes": [
				"SMRTBuses901M",
				"SMRTBuses904",
				"SMRTBuses912",
				"SMRTBuses912A",
				"SMRTBuses913",
				"SMRTBuses964",
				"SMRTBuses965",
				"SMRTBuses969"
			],
			"brands": [
				"SMRTBuses"
			],
			"name": "Admiralty Stn",
			"coords": [
				1.440714,
				103.800708
			],
			"stop_code": "46779",
			"bearing": "S"
		},
		"SingaporeStop_Blk825_E": {
			"live_code": "SingaporeStop_Blk825_E",
			"routes": [
				"SMRTBuses858",
				"SMRTBuses858A",
				"SMRTBuses900",
				"SMRTBuses900A",
				"SMRTBuses904",
				"SMRTBuses911",
				"SMRTBuses913",
				"SMRTBuses964",
				"SMRTBuses965",
				"SMRTBuses965A",
				"SMRTBuses969",
				"SMRTBusesNr2"
			],
			"brands": [
				"SMRTBuses"
			],
			"name": "Blk 825",
			"coords": [
				1.438787,
				103.790026
			],
			"stop_code": "46281",
			"bearing": "E"
		},
		"SingaporeStop_Blk891CCp_W": {
			"live_code": "SingaporeStop_Blk891CCp_W",
			"routes": [
				"SMRTBuses858",
				"SMRTBuses900",
				"SMRTBuses900A",
				"SMRTBuses904",
				"SMRTBuses911",
				"SMRTBuses913",
				"SMRTBuses964",
				"SMRTBuses965",
				"SMRTBuses969"
			],
			"brands": [
				"SMRTBuses"
			],
			"name": "Blk 891C CP",
			"coords": [
				1.438722,
				103.790912
			],
			"stop_code": "46289",
			"bearing": "W"
		},
		"SingaporeStop_Aft888Plaza_W": {
			"live_code": "SingaporeStop_Aft888Plaza_W",
			"routes": [
				"SMRTBuses858",
				"SMRTBuses900",
				"SMRTBuses900A",
				"SMRTBuses904",
				"SMRTBuses913",
				"SMRTBuses964",
				"SMRTBuses965",
				"SMRTBuses969"
			],
			"brands": [
				"SMRTBuses"
			],
			"name": "Aft 888 Plaza",
			"coords": [
				1.43896,
				103.794237
			],
			"stop_code": "46399",
			"bearing": "W"
		},
		"SingaporeStop_BefAdmiraltyPrSch_NW": {
			"live_code": "SingaporeStop_BefAdmiraltyPrSch_NW",
			"routes": [
				"SMRTBuses913",
				"SMRTBuses964"
			],
			"brands": [
				"SMRTBuses"
			],
			"name": "Bef Admiralty Pr Sch",
			"coords": [
				1.442676,
				103.801244
			],
			"stop_code": "46781",
			"bearing": "NW"
		},
		"SingaporeStop_WoodlandsTempInt_N": {
			"live_code": "SingaporeStop_WoodlandsTempInt_N",
			"routes": [
				"SBSTBuses161",
				"SBSTBuses168",
				"SMRTBuses169",
				"SMRTBuses169A",
				"SMRTBuses169B",
				"SMRTBuses178",
				"SMRTBuses178A",
				"SMRTBuses187",
				"SMRTBuses856",
				"SMRTBuses856A",
				"SMRTBuses858",
				"SMRTBuses858A",
				"SMRTBuses900",
				"SMRTBuses900A",
				"SMRTBuses901",
				"SMRTBuses901M",
				"SMRTBuses902",
				"SMRTBuses903",
				"SMRTBuses903M",
				"SMRTBuses904",
				"SMRTBuses911",
				"SMRTBuses912",
				"SMRTBuses912A",
				"SMRTBuses912B",
				"SMRTBuses912M",
				"SMRTBuses913",
				"SMRTBuses913M",
				"SMRTBuses925",
				"SMRTBuses925A",
				"SMRTBuses925M",
				"SMRTBuses926",
				"SMRTBuses950",
				"SMRTBuses960",
				"SMRTBuses960E",
				"SMRTBuses961",
				"SMRTBuses961M",
				"SMRTBuses962",
				"SMRTBuses963",
				"SMRTBuses963R",
				"SMRTBuses963E",
				"SMRTBuses964",
				"SMRTBuses965",
				"SMRTBuses965A",
				"SMRTBuses966",
				"SMRTBuses969"
			],
			"brands": [
				"SBSTBuses",
				"SMRTBuses"
			],
			"name": "W'Lands Temp Int",
			"coords": [
				1.437628,
				103.7865
			],
			"stop_code": "46009",
			"bearing": "NW"
		},
		"SingaporeStop_Blk722_SW": {
			"live_code": "SingaporeStop_Blk722_SW",
			"routes": [
				"SMRTBuses913",
				"SMRTBuses964"
			],
			"brands": [
				"SMRTBuses"
			],
			"name": "Blk 722",
			"coords": [
				1.445695,
				103.799634
			],
			"stop_code": "46791",
			"bearing": "SW"
		},
		"SingaporeStop_Blk15_N": {
			"live_code": "SingaporeStop_Blk15_N",
			"routes": [
				"SMRTBuses964"
			],
			"brands": [
				"SMRTBuses"
			],
			"name": "Blk 15",
			"coords": [
				1.447984,
				103.809515
			],
			"stop_code": "46901",
			"bearing": "N"
		},
		"SingaporeStop_OppNylectEngrg_SW": {
			"live_code": "SingaporeStop_OppNylectEngrg_SW",
			"routes": [
				"SMRTBuses964"
			],
			"brands": [
				"SMRTBuses"
			],
			"name": "Opp Nylect Engrg",
			"coords": [
				1.451673,
				103.805477
			],
			"stop_code": "46941",
			"bearing": "SW"
		},
		"SingaporeStop_Blk786ACp_SE": {
			"live_code": "SingaporeStop_Blk786ACp_SE",
			"routes": [
				"SMRTBuses913",
				"SMRTBuses964"
			],
			"brands": [
				"SMRTBuses"
			],
			"name": "Blk 786A CP",
			"coords": [
				1.445866,
				103.799709
			],
			"stop_code": "46799",
			"bearing": "SE"
		},
		"SingaporeStop_OppWoodlandsMart_E": {
			"live_code": "SingaporeStop_OppWoodlandsMart_E",
			"routes": [
				"SMRTBuses964"
			],
			"brands": [
				"SMRTBuses"
			],
			"name": "Opp W'Lands Mart",
			"coords": [
				1.446497,
				103.798087
			],
			"stop_code": "46809",
			"bearing": "E"
		},
		"SingaporeStop_AftWoodlandsMart_N": {
			"live_code": "SingaporeStop_AftWoodlandsMart_N",
			"routes": [
				"SMRTBuses964"
			],
			"brands": [
				"SMRTBuses"
			],
			"name": "Aft W'Lands Mart",
			"coords": [
				1.446512,
				103.797566
			],
			"stop_code": "46801"
		},
		"SingaporeStop_OppAdmiraltyStn_E": {
			"live_code": "SingaporeStop_OppAdmiraltyStn_E",
			"routes": [
				"SMRTBuses904",
				"SMRTBuses913",
				"SMRTBuses964",
				"SMRTBuses965",
				"SMRTBuses965A",
				"SMRTBuses969"
			],
			"brands": [
				"SMRTBuses"
			],
			"name": "Opp Admiralty Stn",
			"coords": [
				1.440888,
				103.800187
			],
			"stop_code": "46771",
			"bearing": "E"
		},
		"SingaporeStop_OppAdmiraltyPrSch_S": {
			"live_code": "SingaporeStop_OppAdmiraltyPrSch_S",
			"routes": [
				"SMRTBuses913",
				"SMRTBuses964"
			],
			"brands": [
				"SMRTBuses"
			],
			"name": "Opp Admiralty Pr Sch",
			"coords": [
				1.443511,
				103.801063
			],
			"stop_code": "46789",
			"bearing": "S"
		},
		"SingaporeStop_OppBlk773_NE": {
			"live_code": "SingaporeStop_OppBlk773_NE",
			"routes": [
				"SMRTBuses169",
				"SMRTBuses169A",
				"SMRTBuses169B",
				"SMRTBuses858",
				"SMRTBuses858A",
				"SMRTBuses964"
			],
			"brands": [
				"SMRTBuses"
			],
			"name": "Opp Blk 773",
			"coords": [
				1.447969,
				103.797588
			],
			"stop_code": "46471",
			"bearing": "NE"
		},
		"SingaporeStop_Blk706_NE": {
			"live_code": "SingaporeStop_Blk706_NE",
			"routes": [
				"SMRTBuses904",
				"SMRTBuses913",
				"SMRTBuses964",
				"SMRTBuses965",
				"SMRTBuses965A",
				"SMRTBuses969"
			],
			"brands": [
				"SMRTBuses"
			],
			"name": "Blk 706",
			"coords": [
				1.439644,
				103.7974
			],
			"stop_code": "46761",
			"bearing": "NE"
		},
		"SingaporeStop_Blk853_E": {
			"live_code": "SingaporeStop_Blk853_E",
			"routes": [
				"SMRTBuses858",
				"SMRTBuses858A",
				"SMRTBuses900",
				"SMRTBuses900A",
				"SMRTBuses904",
				"SMRTBuses913",
				"SMRTBuses964",
				"SMRTBuses965",
				"SMRTBuses965A",
				"SMRTBuses969",
				"SMRTBusesNr2"
			],
			"brands": [
				"SMRTBuses"
			],
			"name": "Blk 853",
			"coords": [
				1.439218,
				103.792995
			],
			"stop_code": "46391",
			"bearing": "E"
		},
		"SingaporeStop_Blk666_W_1": {
			"live_code": "SingaporeStop_Blk666_W_1",
			"routes": [
				"SMRTBuses904",
				"SMRTBuses913",
				"SMRTBuses964",
				"SMRTBuses965",
				"SMRTBuses969"
			],
			"brands": [
				"SMRTBuses"
			],
			"name": "Blk 666",
			"coords": [
				1.439351,
				103.797358
			],
			"stop_code": "46769",
			"bearing": "W"
		}
	},
	"feeds": [],
	"status": 0
}